deepehrgraph/__init__.py
deepehrgraph/dataset/__init__.py
deepehrgraph/dataset/dataset.py
deepehrgraph/dataset/eda.py
deepehrgraph/dataset/features_selection.py
deepehrgraph/dataset/legacy/helpers.py
deepehrgraph/dataset/legacy/medcode_utils.py
deepehrgraph/dataset/legacy/medcodes/__init__.py
deepehrgraph/dataset/legacy/medcodes/diagnoses/__init__.py
deepehrgraph/dataset/legacy/medcodes/diagnoses/_mappers/__init__.py
deepehrgraph/dataset/legacy/medcodes/diagnoses/_mappers/elixhauser_charlson.py
deepehrgraph/dataset/legacy/medcodes/diagnoses/_mappers/icd10_descriptions.py
deepehrgraph/dataset/legacy/medcodes/diagnoses/_mappers/icd10to9_dict.py
deepehrgraph/dataset/legacy/medcodes/diagnoses/_mappers/icd9_descriptions.py
deepehrgraph/dataset/legacy/medcodes/diagnoses/_mappers/icd9to10_dict.py
deepehrgraph/dataset/legacy/medcodes/diagnoses/comorbidities.py
deepehrgraph/dataset/legacy/medcodes/diagnoses/icd_conversion.py
deepehrgraph/dataset/legacy/medcodes/drugs/__init__.py
deepehrgraph/dataset/legacy/medcodes/drugs/_mappers/__init__.py
deepehrgraph/dataset/legacy/medcodes/drugs/_mappers/_lv1.py
deepehrgraph/dataset/legacy/medcodes/drugs/_mappers/_lv2.py
deepehrgraph/dataset/legacy/medcodes/drugs/_mappers/_lv3.py
deepehrgraph/dataset/legacy/medcodes/drugs/_mappers/_lv4.py
deepehrgraph/dataset/legacy/medcodes/drugs/_mappers/_lv5.py
deepehrgraph/dataset/legacy/medcodes/drugs/classification.py
deepehrgraph/dataset/legacy/medcodes/drugs/standardization.py
deepehrgraph/logger.py
deepehrgraph/main.py
deepehrgraph/training/__init__.py
deepehrgraph/training/dataset.py
deepehrgraph/training/enums.py
deepehrgraph/training/models.py
deepehrgraph/training/train.py
deepehrgraph-0.3.4.dist-info/LICENSE
deepehrgraph-0.3.4.dist-info/METADATA
deepehrgraph-0.3.4.dist-info/WHEEL
deepehrgraph-0.3.4.dist-info/entry_points.txt
deepehrgraph-0.3.4.dist-info/RECORD
