Metadata-Version: 2.1
Name: deepehrgraph
Version: 0.3.4
Summary: 
Author: francois.cokelaer
Author-email: francois.cokelaer@gmail.com
Requires-Python: >=3.10,<3.13
Classifier: Programming Language :: Python :: 3
Classifier: Programming Language :: Python :: 3.10
Classifier: Programming Language :: Python :: 3.11
Classifier: Programming Language :: Python :: 3.12
Requires-Dist: imblearn (>=0.0,<0.1)
Requires-Dist: lightning (>=2.1.1,<3.0.0)
Requires-Dist: matplotlib (>=3.8.1,<4.0.0)
Requires-Dist: pandas (>=1.5.3,<2.0.0)
Requires-Dist: scikit-learn (==1.2.2)
Requires-Dist: seaborn (>=0.13.0,<0.14.0)
Requires-Dist: statsmodels (>=0.14.0,<0.15.0)
Requires-Dist: tensorboard (>=2.14,<3.0)
Requires-Dist: tensorboardx (>=2.6.2.2,<3.0.0.0)
Requires-Dist: torchmetrics (>=1.2.0,<2.0.0)
